smalldog/__init__.py
smalldog/quantityu.py
smalldog/temptoolclass_pydocument.py
smalldog/temptoolclass_version.py
smalldog/valueu.py
smalldog-0.2539.3.dist-info/METADATA
smalldog-0.2539.3.dist-info/WHEEL
smalldog-0.2539.3.dist-info/entry_points.txt
smalldog-0.2539.3.dist-info/RECORD
