Metadata-Version: 2.4
Name: smalldog
Version: 0.2539.3
Summary: Testing field of evaluation for pre-release package (alpha)
Project-URL: Homepage, https://kohdh.com/
Author-email: Donghyeok Koh <donghyeok.koh.code@gmail.com>
License: Other/Proprietary License
Classifier: Development Status :: 3 - Alpha
Classifier: Intended Audience :: Science/Research
Classifier: License :: Other/Proprietary License
Classifier: Operating System :: OS Independent
Classifier: Programming Language :: Python :: 3
Classifier: Topic :: Scientific/Engineering :: Astronomy
Requires-Python: >=3.6
Requires-Dist: astropy
Requires-Dist: numpy>=1.23.2
Requires-Dist: scipy>=1.9.2
